gfss_placeholder/__init__.py
gfss_logger-0.0.1.dist-info/METADATA
gfss_logger-0.0.1.dist-info/WHEEL
gfss_logger-0.0.1.dist-info/top_level.txt
gfss_logger-0.0.1.dist-info/RECORD
