Metadata-Version: 2.1
Name: gfss-logger
Version: 0.0.1
Summary: gfss_placeholder
Home-page: UNKNOWN
Author: John, Doe
Author-email: John.Doe@doe.com
License: UNKNOWN
Platform: UNKNOWN
Classifier: Programming Language :: Python :: 3
Classifier: License :: OSI Approved :: MIT License
Classifier: Operating System :: OS Independent
Requires-Python: >=3.6
